setup.py
estools/__init__.py
estools.egg-info/PKG-INFO
estools.egg-info/SOURCES.txt
estools.egg-info/dependency_links.txt
estools.egg-info/entry_points.txt
estools.egg-info/requires.txt
estools.egg-info/top_level.txt
estools/command/__init__.py
estools/command/river.py
estools/command/rotate.py
estools/command/template.py