Metadata-Version: 1.0
Name: estools
Version: 1.1.0
Summary: estools: tools for interacting with elasticsearch
Home-page: https://github.com/alphagov/estools
Author: Government Digital Service
Author-email: nick@whiteink.com
License: MIT
Keywords: sysadmin search elasticsearch templates rivers
Platform: UNKNOWN
